nonebot_plugin_ba_tools/__init__.py
nonebot_plugin_ba_tools/config.py
nonebot_plugin_ba_tools/default_config.yaml
nonebot_plugin_ba_tools/get_ba_activity_info/__init__.py
nonebot_plugin_ba_tools/get_ba_better_student/__init__.py
nonebot_plugin_ba_tools/get_ba_clairvoyance/__init__.py
nonebot_plugin_ba_tools/get_ba_manga/__init__.py
nonebot_plugin_ba_tools/get_ba_pics/__init__.py
nonebot_plugin_ba_tools/get_ba_pics/models.py
nonebot_plugin_ba_tools/get_ba_raid_line/__init__.py
nonebot_plugin_ba_tools/get_ba_simple_appraise/__init__.py
nonebot_plugin_ba_tools/get_ba_student_birthday/__init__.py
nonebot_plugin_ba_tools/get_ba_student_birthday/fonts/ComicShannsMonoNerdFont-Regular.otf
nonebot_plugin_ba_tools/get_ba_student_birthday/fonts/miaozi-meiweiti-2.ttf
nonebot_plugin_ba_tools/get_ba_student_birthday/utils/draw_img.py
nonebot_plugin_ba_tools/get_ba_student_info/__init__.py
nonebot_plugin_ba_tools/get_ba_walkthrough/__init__.py
nonebot_plugin_ba_tools/llm/__init__.py
nonebot_plugin_ba_tools/llm/client.py
nonebot_plugin_ba_tools/llm/commands.py
nonebot_plugin_ba_tools/llm/models.py
nonebot_plugin_ba_tools/llm/prompts.yaml
nonebot_plugin_ba_tools/llm/utils/__init__.py
nonebot_plugin_ba_tools/send_battle_info/__init__.py
nonebot_plugin_ba_tools/send_battle_info/command.py
nonebot_plugin_ba_tools/send_battle_info/utils/common.py
nonebot_plugin_ba_tools/send_battle_info/utils/reponse/dynamic_list.py
nonebot_plugin_ba_tools/send_battle_info/utils/services.py
nonebot_plugin_ba_tools/send_birthday_info/__init__.py
nonebot_plugin_ba_tools/send_birthday_info/command.py
nonebot_plugin_ba_tools/utils/addition_for_htmlrender.py
nonebot_plugin_ba_tools/utils/common.py
nonebot_plugin_ba_tools/utils/constants.py
nonebot_plugin_ba_tools/utils/dataloader.py
nonebot_plugin_ba_tools/utils/get_img_from_name.py
nonebot_plugin_ba_tools/utils/get_info.py
nonebot_plugin_ba_tools/utils/types.py
nonebot_plugin_ba_tools/utils/user_info.py
nonebot_plugin_ba_tools/utils/wiki.py
nonebot_plugin_ba_tools-0.5.9.post2.dist-info/LICENSE
nonebot_plugin_ba_tools-0.5.9.post2.dist-info/METADATA
nonebot_plugin_ba_tools-0.5.9.post2.dist-info/WHEEL
nonebot_plugin_ba_tools-0.5.9.post2.dist-info/RECORD
