Metadata-Version: 2.3
Name: nonebot-plugin-ba-tools
Version: 0.5.9.post2
Summary: 一个BlueArchive工具箱
License: MIT
Author: hanasaki
Author-email: hanasakayui2022@gmail.com
Requires-Python: >=3.9,<4.0
Classifier: License :: OSI Approved :: MIT License
Classifier: Programming Language :: Python :: 3
Classifier: Programming Language :: Python :: 3.9
Classifier: Programming Language :: Python :: 3.10
Classifier: Programming Language :: Python :: 3.11
Classifier: Programming Language :: Python :: 3.12
Classifier: Programming Language :: Python :: 3.13
Requires-Dist: beautifulsoup4 (>=4.12.3,<5.0.0)
Requires-Dist: deepdiff (>=8.1.1,<9.0.0)
Requires-Dist: httpx (>=0.27.0,<0.29.0)
Requires-Dist: nonebot-plugin-alconna (>=0.54.2,<0.55.0)
Requires-Dist: nonebot-plugin-apscheduler (>=0.5.0,<0.6.0)
Requires-Dist: nonebot-plugin-htmlrender (>=0.5.1,<0.6.0)
Requires-Dist: nonebot-plugin-localstore (>=0.7.1,<0.8.0)
Requires-Dist: nonebot-plugin-uninfo (>=0.5.0,<0.7.0)
Requires-Dist: nonebot2[fastapi] (>=2,<3)
Requires-Dist: openai (>=1.60.2,<2.0.0)
Requires-Dist: pillow (>=10.4.0,<11.0.0)
Requires-Dist: psutil (>=6.1.1,<7.0.0)
Requires-Dist: pydantic (>=1.0,<3.0.0)
Requires-Dist: pyjwt (>=2.10.1,<3.0.0)
Requires-Dist: pyyaml (>=6.0.2,<7.0.0)
Project-URL: Homepage, https://github.com/hanasa2023/nonebot-plugin-ba-tools#readme
Project-URL: Repository, https://github.com/hanasa2023/nonebot-plugin-ba-tools
